<?xml version="1.0" encoding="UTF-8" standalone="yes"?>
<pluginstrument>
    <aircraft>Cessna 172</aircraft>
    <author>Jason Tatum</author>
    <compatibleFSX>true</compatibleFSX>
    <compatibleP3D>true</compatibleP3D>
    <compatibleXPL>true</compatibleXPL>
    <configVersion>1</configVersion>
    <description></description>
    <pluginInterfaceVersion>100</pluginInterfaceVersion>
    <prefHeight>512</prefHeight>
    <prefWidth>512</prefWidth>
    <type>Vacuum &amp; Ameter</type>
    <uuid>c65b9290-e215-45be-badb-22289cedc743</uuid>
    <version>1</version>
</pluginstrument>
